LICENSE
MANIFEST.in
README.rst
pyproject.toml
setup.cfg
setup.py
cf_django_oauth_toolkit.egg-info/PKG-INFO
cf_django_oauth_toolkit.egg-info/SOURCES.txt
cf_django_oauth_toolkit.egg-info/dependency_links.txt
cf_django_oauth_toolkit.egg-info/not-zip-safe
cf_django_oauth_toolkit.egg-info/requires.txt
cf_django_oauth_toolkit.egg-info/top_level.txt
oauth2_provider/__init__.py
oauth2_provider/admin.py
oauth2_provider/apps.py
oauth2_provider/backends.py
oauth2_provider/compat.py
oauth2_provider/decorators.py
oauth2_provider/exceptions.py
oauth2_provider/forms.py
oauth2_provider/generators.py
oauth2_provider/http.py
oauth2_provider/middleware.py
oauth2_provider/models.py
oauth2_provider/oauth2_backends.py
oauth2_provider/oauth2_validators.py
oauth2_provider/scopes.py
oauth2_provider/settings.py
oauth2_provider/signals.py
oauth2_provider/urls.py
oauth2_provider/validators.py
oauth2_provider/contrib/__init__.py
oauth2_provider/contrib/rest_framework/__init__.py
oauth2_provider/contrib/rest_framework/authentication.py
oauth2_provider/contrib/rest_framework/permissions.py
oauth2_provider/management/__init__.py
oauth2_provider/management/commands/__init__.py
oauth2_provider/management/commands/cleartokens.py
oauth2_provider/management/commands/createapplication.py
oauth2_provider/migrations/0001_initial.py
oauth2_provider/migrations/0002_auto_20190406_1805.py
oauth2_provider/migrations/0003_auto_20201211_1314.py
oauth2_provider/migrations/__init__.py
oauth2_provider/templates/oauth2_provider/application_confirm_delete.html
oauth2_provider/templates/oauth2_provider/application_detail.html
oauth2_provider/templates/oauth2_provider/application_form.html
oauth2_provider/templates/oauth2_provider/application_list.html
oauth2_provider/templates/oauth2_provider/application_registration_form.html
oauth2_provider/templates/oauth2_provider/authorize.html
oauth2_provider/templates/oauth2_provider/authorized-oob.html
oauth2_provider/templates/oauth2_provider/authorized-token-delete.html
oauth2_provider/templates/oauth2_provider/authorized-tokens.html
oauth2_provider/templates/oauth2_provider/base.html
oauth2_provider/views/__init__.py
oauth2_provider/views/application.py
oauth2_provider/views/base.py
oauth2_provider/views/generic.py
