Metadata-Version: 2.1
Name: cf-django-oauth-toolkit
Version: 1.3.4
Summary: OAuth2 Provider for Django
Home-page: https://github.com/jazzband/django-oauth-toolkit
Author: Federico Frenguelli, Massimiliano Pippi
Author-email: synasius@gmail.com
License: UNKNOWN
Keywords: django,oauth,oauth2,oauthlib
Platform: UNKNOWN
Classifier: Development Status :: 5 - Production/Stable
Classifier: Environment :: Web Environment
Classifier: Framework :: Django
Classifier: Framework :: Django :: 2.2
Classifier: Framework :: Django :: 3.0
Classifier: Framework :: Django :: 3.1
Classifier: Intended Audience :: Developers
Classifier: License :: OSI Approved :: BSD License
Classifier: Operating System :: OS Independent
Classifier: Programming Language :: Python :: 3
Classifier: Programming Language :: Python :: 3.5
Classifier: Programming Language :: Python :: 3.6
Classifier: Programming Language :: Python :: 3.7
Classifier: Programming Language :: Python :: 3.8
Classifier: Programming Language :: Python :: 3.9
Classifier: Topic :: Internet :: WWW/HTTP
